ColorfulOutput/ColorfulOutput.py
ColorfulOutput/__init__.py
ColorfulOutput-0.0.1.dist-info/LICENSE
ColorfulOutput-0.0.1.dist-info/METADATA
ColorfulOutput-0.0.1.dist-info/WHEEL
ColorfulOutput-0.0.1.dist-info/top_level.txt
ColorfulOutput-0.0.1.dist-info/RECORD
