Metadata-Version: 2.1
Name: ColorfulOutput
Version: 0.0.1
Summary: Adds colors to your console prints.
Home-page: https://github.com/RasseTheBoy/ColorfulOutput
Author: Rasmus Ohert
Author-email: Rasmus Ohert <rassemichael@gmail.com>
License: MIT License
Project-URL: Repository, https://github.com/RasseTheBoy/ColorfulOutput
Keywords: python,console,colors,print
Classifier: Development Status :: 5 - Production/Stable
Classifier: Intended Audience :: Education
Classifier: Programming Language :: Python :: 3
Classifier: Operating System :: OS Independent
Classifier: License :: OSI Approved :: MIT License
Requires-Python: >=3.5
License-File: LICENSE
